zycelium/ansiformat/__init__.py
zycelium/ansiformat/color.py
zycelium/ansiformat/format.py
zycelium/ansiformat/markup.py
zycelium/ansiformat/palette.py
zycelium/ansiformat/string.py
zycelium.ansiformat-0.1.1.dist-info/LICENSE
zycelium.ansiformat-0.1.1.dist-info/METADATA
zycelium.ansiformat-0.1.1.dist-info/WHEEL
zycelium.ansiformat-0.1.1.dist-info/top_level.txt
zycelium.ansiformat-0.1.1.dist-info/RECORD
