Metadata-Version: 2.1
Name: zycelium.ansiformat
Version: 0.1.1
Summary: ANSI Formatted Text for Terminals.
Home-page: https://github.com/zycelium/python-ansiformat
Author: Harshad Sharma
Author-email: harshad@sharma.io
License: UNKNOWN
Project-URL: Bug Tracker, https://github.com/zycelium/python-ansiformat/issues
Platform: UNKNOWN
Classifier: Programming Language :: Python :: 3
Classifier: License :: OSI Approved :: BSD License
Classifier: Operating System :: OS Independent
Classifier: Development Status :: 3 - Alpha
Requires-Python: >=3.7
License-File: LICENSE
Requires-Dist: sty (>=1.0.0rc1)
Requires-Dist: colour (>=0.1.5)
Provides-Extra: devel
Requires-Dist: bump2version (>=1.0) ; extra == 'devel'
Requires-Dist: pytest (>=6.2) ; extra == 'devel'
